network/__init__.py
network/ssh.py
shikoulib-1.0.0.dist-info/METADATA
shikoulib-1.0.0.dist-info/WHEEL
shikoulib-1.0.0.dist-info/top_level.txt
shikoulib-1.0.0.dist-info/RECORD
