Metadata-Version: 2.4
Name: shikoulib
Version: 1.0.0
Summary: A short description
License: MIT
Project-URL: Homepage, https://github.com/shikou-git/shikoulib
Project-URL: Repository, https://github.com/shikou-git/shikoulib
Requires-Python: >=3.10
Requires-Dist: paramiko
Requires-Dist: loguru
